symphony_hierarchical_confusion_matrix/__init__.py
symphony_hierarchical_confusion_matrix/_frontend.py
symphony_hierarchical_confusion_matrix/_version.py
symphony_hierarchical_confusion_matrix/widget.py
symphony_hierarchical_confusion_matrix/labextension/build_log.json
symphony_hierarchical_confusion_matrix/labextension/package.json
symphony_hierarchical_confusion_matrix/labextension/static/lib_index_js.46a03b38e4569e90dced.js
symphony_hierarchical_confusion_matrix/labextension/static/lib_index_js.46a03b38e4569e90dced.js.map
symphony_hierarchical_confusion_matrix/labextension/static/remoteEntry.5bfa3819b698356bdedc.js
symphony_hierarchical_confusion_matrix/labextension/static/remoteEntry.5bfa3819b698356bdedc.js.map
symphony_hierarchical_confusion_matrix/labextension/static/style.js
symphony_hierarchical_confusion_matrix/nbextension/extension.js
symphony_hierarchical_confusion_matrix/nbextension/index.js
symphony_hierarchical_confusion_matrix/standalone/favicon.png
symphony_hierarchical_confusion_matrix/standalone/index.html
symphony_hierarchical_confusion_matrix/standalone/script.js
symphony_hierarchical_confusion_matrix/standalone/data/SymphonyHierarchicalConfusionMatrix.json
symphony_hierarchical_confusion_matrix/standalone/data/SymphonySummary.json
symphony_hierarchical_confusion_matrix/standalone/data/table.arrow
symphony_hierarchical_confusion_matrix/standalone/data/widget_info.json
symphony_hierarchical_confusion_matrix/standalone/widgets/StandaloneApp.js
symphony_hierarchical_confusion_matrix/standalone/widgets/StandaloneApp.js.map
symphony_hierarchical_confusion_matrix/standalone/widgets/SymphonyHierarchicalConfusionMatrix.js
symphony_hierarchical_confusion_matrix/standalone/widgets/SymphonyHierarchicalConfusionMatrix.js.map
symphony_hierarchical_confusion_matrix/standalone/widgets/SymphonySummary.js
symphony_hierarchical_confusion_matrix/standalone/widgets/SymphonySummary.js.map
symphony_hierarchical_confusion_matrix-1.0.3.dist-info/LICENSE.txt
symphony_hierarchical_confusion_matrix-1.0.3.dist-info/METADATA
symphony_hierarchical_confusion_matrix-1.0.3.dist-info/WHEEL
symphony_hierarchical_confusion_matrix-1.0.3.dist-info/top_level.txt
symphony_hierarchical_confusion_matrix-1.0.3.dist-info/RECORD
